isitfit/__init__.py
isitfit/apiMan.py
isitfit/dotMan.py
isitfit/emailMan.py
isitfit/sentry_proxy.py
isitfit/tqdmman.py
isitfit/utils.py
isitfit/cli/__init__.py
isitfit/cli/click_descendents.py
isitfit/cli/core.py
isitfit/cli/cost.py
isitfit/cli/datadog.py
isitfit/cli/issue10.py
isitfit/cli/tags.py
isitfit/cli/version.py
isitfit/cost/__init__.py
isitfit/cost/account_cost_analyze.py
isitfit/cost/account_cost_optimize.py
isitfit/cost/base_iterator.py
isitfit/cost/base_reporter.py
isitfit/cost/cacheManager.py
isitfit/cost/catalog_ec2.py
isitfit/cost/catalog_redshift.py
isitfit/cost/cloudtrail_ec2type.py
isitfit/cost/cloudtrail_iterator.py
isitfit/cost/ec2_analyze.py
isitfit/cost/ec2_common.py
isitfit/cost/ec2_optimize.py
isitfit/cost/mainManager.py
isitfit/cost/metrics_automatic.py
isitfit/cost/metrics_cloudwatch.py
isitfit/cost/metrics_datadog.py
isitfit/cost/redshift_analyze.py
isitfit/cost/redshift_common.py
isitfit/cost/redshift_optimize.py
isitfit/migrations/__init__.py
isitfit/migrations/cli.py
isitfit/migrations/miglist.py
isitfit/migrations/migman.py
isitfit/tags/__init__.py
isitfit/tags/tagsCsvDiff.py
isitfit/tags/tagsDump.py
isitfit/tags/tagsImplier.py
isitfit/tags/tagsPush.py
isitfit/tags/tagsSuggestAdvanced.py
isitfit/tags/tagsSuggestBasic.py
isitfit/tests/__init__.py
isitfit/tests/test_apiMan.py
isitfit/tests/test_click.py
isitfit/tests/test_dotMan.py
isitfit/tests/test_emailMan_functional.py
isitfit/tests/test_emailMan_unit.py
isitfit/tests/test_pythonException.py
isitfit/tests/test_sentryProxy.py
isitfit/tests/test_tqdmman.py
isitfit/tests/test_utils.py
isitfit/tests/cost/__init__.py
isitfit/tests/cost/test_accountCostAnalyze.py
isitfit/tests/cost/test_accountCostOptimize.py
isitfit/tests/cost/test_cloudtrail_iterator_functional.py
isitfit/tests/cost/test_ec2Analyze.py
isitfit/tests/cost/test_mainManager.py
isitfit/tests/cost/test_metricsAutomatic.py
isitfit/tests/cost/test_metricsCloudwatch_functional.py
isitfit/tests/cost/test_metricsCloudwatch_unit.py
isitfit-0.20.11.dist-info/LICENSE
isitfit-0.20.11.dist-info/METADATA
isitfit-0.20.11.dist-info/WHEEL
isitfit-0.20.11.dist-info/entry_points.txt
isitfit-0.20.11.dist-info/top_level.txt
isitfit-0.20.11.dist-info/RECORD
