Metadata-Version: 2.1
Name: isitfit
Version: 0.20.11
Summary: Command-line tool to calculate excess AWS cloud resource capacity
Home-page: https://gitlab.com/autofitcloud/isitfit
Author: Shadi Akiki, AutofitCloud
Author-email: shadi@autofitcloud.com
License: UNKNOWN
Platform: UNKNOWN
Requires-Dist: click (==7.0)
Requires-Dist: pandas (==0.25.1)
Requires-Dist: requests (==2.22.0)
Requires-Dist: cachecontrol (==0.12.5)
Requires-Dist: lockfile (==0.12.2)
Requires-Dist: tabulate (==0.8.3)
Requires-Dist: termcolor (==1.1.0)
Requires-Dist: tqdm (==4.32.2)
Requires-Dist: redis (==3.3.8)
Requires-Dist: pyarrow (==0.15.0)
Requires-Dist: awscli (==1.16.248)
Requires-Dist: boto3 (==1.9.238)
Requires-Dist: datadog (==0.30.0)
Requires-Dist: schema (==0.7.1)
Requires-Dist: visidata (==1.5.2)
Requires-Dist: outdated (==0.2.0)
Requires-Dist: aws-requests-auth (==0.4.2)
Requires-Dist: matomo-sdk-py (==0.2.1)
Requires-Dist: simple-cache (==0.35)
Requires-Dist: sentry-sdk (==0.13.5)
Requires-Dist: pytest (==5.2.1)
